README.md
setup.cfg
setup.py
distributions/Binomialdistribution.py
distributions/Gaussiandistribution.py
distributions/Generaldistribution.py
distributions/__init__.py
econ_distributions.egg-info/PKG-INFO
econ_distributions.egg-info/SOURCES.txt
econ_distributions.egg-info/dependency_links.txt
econ_distributions.egg-info/not-zip-safe
econ_distributions.egg-info/top_level.txt