Metadata-Version: 1.0
Name: econ-distributions
Version: 0.1
Summary: Gaussian distributions
Home-page: UNKNOWN
Author: Satyajit Ovelil
Author-email: UNKNOWN
License: UNKNOWN
Platform: UNKNOWN
